rocketry/__init__.py
rocketry/_base.py
rocketry/_setup.py
rocketry/_version.py
rocketry/application.py
rocketry/exc.py
rocketry/session.py
rocketry/args/__init__.py
rocketry/args/builtin.py
rocketry/args/secret.py
rocketry/conditions/__init__.py
rocketry/conditions/api.py
rocketry/conditions/func.py
rocketry/conditions/meta.py
rocketry/conditions/parameter.py
rocketry/conditions/scheduler.py
rocketry/conditions/time.py
rocketry/conditions/task/__init__.py
rocketry/conditions/task/task.py
rocketry/conditions/task/utils.py
rocketry/conds/__init__.py
rocketry/core/__init__.py
rocketry/core/hook.py
rocketry/core/meta.py
rocketry/core/schedule.py
rocketry/core/task.py
rocketry/core/condition/__init__.py
rocketry/core/condition/base.py
rocketry/core/log/__init__.py
rocketry/core/log/adapter.py
rocketry/core/parameters/__init__.py
rocketry/core/parameters/arguments.py
rocketry/core/parameters/parameters.py
rocketry/core/time/__init__.py
rocketry/core/time/anchor.py
rocketry/core/time/base.py
rocketry/core/time/utils.py
rocketry/core/utils/__init__.py
rocketry/core/utils/meta.py
rocketry/core/utils/pickle.py
rocketry/core/utils/process.py
rocketry/log/__init__.py
rocketry/log/defaults.py
rocketry/log/handlers.py
rocketry/log/log_record.py
rocketry/log/utils.py
rocketry/parameters/__init__.py
rocketry/parameters/func.py
rocketry/parse/__init__.py
rocketry/parse/_setup_cond_parsers.py
rocketry/parse/condition.py
rocketry/parse/time.py
rocketry/parse/_condition/__init__.py
rocketry/parse/_condition/condition_item.py
rocketry/parse/_condition/string.py
rocketry/parse/_time/__init__.py
rocketry/parse/_time/string.py
rocketry/parse/_time/time_item.py
rocketry/parse/utils/__init__.py
rocketry/parse/utils/cond.py
rocketry/parse/utils/exception.py
rocketry/parse/utils/parser.py
rocketry/parse/utils/string_parser.py
rocketry/parse/utils/utils.py
rocketry/pybox/__init__.py
rocketry/pybox/container/__init__.py
rocketry/pybox/container/visitor.py
rocketry/pybox/pkg/__init__.py
rocketry-2.1.2.dist-info/LICENSE
rocketry-2.1.2.dist-info/METADATA
rocketry-2.1.2.dist-info/WHEEL
rocketry-2.1.2.dist-info/top_level.txt
rocketry-2.1.2.dist-info/RECORD
