Metadata-Version: 2.1
Name: rocketry
Version: 2.1.2
Summary: Advanced scheduling framework
Home-page: https://github.com/Miksus/rocketry.git
Author: Mikael Koli
Author-email: koli.mikael@gmail.com
Classifier: Development Status :: 5 - Production/Stable
Classifier: License :: OSI Approved :: MIT License
Classifier: Operating System :: OS Independent
Classifier: Programming Language :: Python :: 3
Classifier: Programming Language :: Python :: 3.7
Classifier: Programming Language :: Python :: 3.8
Classifier: Programming Language :: Python :: 3.9
Classifier: Programming Language :: Python :: 3.10
Classifier: Topic :: Software Development
Classifier: Topic :: Software Development :: Libraries
Classifier: Topic :: Software Development :: Libraries :: Application Frameworks
Classifier: Topic :: Office/Business :: Scheduling
Classifier: Topic :: System
Classifier: Intended Audience :: Developers
Classifier: Intended Audience :: System Administrators
Classifier: Intended Audience :: Information Technology
Requires-Python: >=3.7.0
License-File: LICENSE
Requires-Dist: python-dateutil
Requires-Dist: redbird (>=0.5.0)
Requires-Dist: pydantic
